{
    "test_name": "render_app_test",
    "description": "Test Name: Home Page Test\nGoal: Verify the home page loads and shows expected content.\nURL: https://ai-test-automation-demo.onrender.com/\n\nSteps:\n1. Navigate to the home page.\n2. Verify the page loads successfully.\n3. Verify the heading \"Hello from your Flask Demo App!\" is visible.\n4. Verify the \"Login\" link is visible.\n5. Click the \"Login\" link.\n6. Verify the browser navigates to /login.\n\nExpected Result:\nThe home page loads and displays the correct heading and login link.\n",
    "steps": [
        {
            "action": "navigate",
            "target": "url",
            "value": "https://ai-test-automation-demo.onrender.com/",
            "selector": null
        },
        {
            "action": "navigate",
            "target": "url",
            "value": "https://ai-test-automation-demo.onrender.com/login",
            "selector": null
        },
        {
            "action": "click",
            "target": "login_button",
            "selector": "button[type='submit']"
        }
    ],
    "metadata": {
        "priority": "high"
    }
}